brewfile/__init__.py
brewfile/brew.py
brewfile/cli.py
brewfile/manager.py
brewfile/models.py
brewfile/utils.py
brewfile-0.1.5.dist-info/METADATA
brewfile-0.1.5.dist-info/WHEEL
brewfile-0.1.5.dist-info/entry_points.txt
brewfile-0.1.5.dist-info/top_level.txt
brewfile-0.1.5.dist-info/RECORD
