Metadata-Version: 2.4
Name: brewfile
Version: 0.1.5
Summary: Intelligent Homebrew package management using brew bundle with JSON configuration and machine-aware installations
Author-email: Walter Mwaniki <walter.g.mwaniki@gmail.com>
Project-URL: Homepage, https://github.com/waltermwaniki/brewfile
Project-URL: Repository, https://github.com/waltermwaniki/brewfile
Project-URL: Issues, https://github.com/waltermwaniki/brewfile/issues
Keywords: homebrew,brew,package-management,macos,cli
Classifier: Development Status :: 4 - Beta
Classifier: Environment :: Console
Classifier: Intended Audience :: Developers
Classifier: License :: OSI Approved :: MIT License
Classifier: Operating System :: MacOS
Classifier: Programming Language :: Python :: 3
Classifier: Programming Language :: Python :: 3.9
Classifier: Programming Language :: Python :: 3.10
Classifier: Programming Language :: Python :: 3.11
Classifier: Programming Language :: Python :: 3.12
Classifier: Programming Language :: Python :: 3.13
Classifier: Topic :: System :: Installation/Setup
Classifier: Topic :: System :: Software Distribution
Requires-Python: >=3.9
